qolsys_client/__init__.py
qolsys_client/arm.py
qolsys_client/main.py
qolsys_client/mqtt_client.py
qolsys_client/mqtt_subscriber.py
qolsys_client/qolsys_socket.py
qolsys_client-0.1.0.dist-info/LICENSE
qolsys_client-0.1.0.dist-info/METADATA
qolsys_client-0.1.0.dist-info/WHEEL
qolsys_client-0.1.0.dist-info/top_level.txt
qolsys_client-0.1.0.dist-info/RECORD
