Metadata-Version: 2.1
Name: qolsys-client
Version: 0.1.0
Summary: A client for Qolsys alarm panels
Home-page: https://github.com/mzac/qolsys_client
Author: Zachary McGibbon
Author-email: zachary.mcgibbon@gmail.com
License: UNKNOWN
Project-URL: Bug Tracker, https://github.com/mzac/qolsys_client/issues
Platform: UNKNOWN
Classifier: Programming Language :: Python :: 3
Classifier: License :: OSI Approved :: MIT License
Classifier: Operating System :: OS Independent
Requires-Python: >=3.6
